smeval/__init__.py
smeval/common/__init__.py
smeval/tools/EvalDet.py
smeval/tools/__init__.py
smeval/tools/evalcls.py
SmEval-0.1.2.dist-info/METADATA
SmEval-0.1.2.dist-info/WHEEL
SmEval-0.1.2.dist-info/top_level.txt
SmEval-0.1.2.dist-info/RECORD
