Metadata-Version: 2.1
Name: SmEval
Version: 0.1.2
Summary: ShanMa Eval Toolbox
Home-page: https://git.supremind.info/algorithmteam/suprevideo/evaltools
Author: zhaozhijian
Author-email: UNKNOWN
License: UNKNOWN
Keywords: evaluation
Platform: UNKNOWN
Classifier: Development Status :: 4 - Beta
Classifier: License :: OSI Approved :: Apache Software License
Classifier: Operating System :: OS Independent
Classifier: Programming Language :: Python :: 2
Classifier: Programming Language :: Python :: 2.7
Classifier: Programming Language :: Python :: 3
Classifier: Programming Language :: Python :: 3.4
Classifier: Programming Language :: Python :: 3.5
Classifier: Programming Language :: Python :: 3.6
Requires-Dist: numpy
Requires-Dist: matplotlib
